goldensphinx/__init__.py
goldensphinx/_version.py
goldensphinx/cli.py
goldensphinx-0.0.3.dist-info/DESCRIPTION.rst
goldensphinx-0.0.3.dist-info/METADATA
goldensphinx-0.0.3.dist-info/RECORD
goldensphinx-0.0.3.dist-info/WHEEL
goldensphinx-0.0.3.dist-info/entry_points.txt
goldensphinx-0.0.3.dist-info/metadata.json
goldensphinx-0.0.3.dist-info/top_level.txt
