Metadata-Version: 2.0
Name: goldensphinx
Version: 0.0.3
Summary: Build and serve Sphinx
Home-page: https://github.com/yoavram/goldensphinx
Author: Yoav Ram
Author-email: yoav@yoavram.com
License: MIT
Platform: UNKNOWN
Requires-Dist: click (>=5sphinx>=1.3.0)
Requires-Dist: gevent (>=0.13.6)
Requires-Dist: greenlet (>=0.3.1)
Requires-Dist: gunicorn (>=0.13.4)
Requires-Dist: numpydoc
Requires-Dist: sphinx-rtd-theme
Requires-Dist: static
Requires-Dist: static (>=0.4)
